.gitignore
CHANGES.txt
LICENSE
README.rst
pytest.ini
requirements.txt
setup.py
tox.ini
zbx_template_celery.xml
src/celery_zabbix/__init__.py
src/celery_zabbix/conftest.py
src/celery_zabbix/receiver.py
src/celery_zabbix.egg-info/PKG-INFO
src/celery_zabbix.egg-info/SOURCES.txt
src/celery_zabbix.egg-info/dependency_links.txt
src/celery_zabbix.egg-info/entry_points.txt
src/celery_zabbix.egg-info/not-zip-safe
src/celery_zabbix.egg-info/requires.txt
src/celery_zabbix.egg-info/top_level.txt
src/celery_zabbix/tests/__init__.py
src/celery_zabbix/tests/test_receiver.py