Metadata-Version: 1.0
Name: celery-zabbix
Version: 1.0.3
Summary: Sends task execution metrics to Zabbix
Home-page: https://github.com/zeitonline/celery_zabbix
Author: Zeit Online
Author-email: zon-backend@zeit.de
License: BSD
Platform: UNKNOWN
